loger/__init__.py
loger/config_server_log.py
src/__init__.py
src/descriptor.py
src/metaclasses.py
src/server.py
src/utils.py
src/variables.py
shark_ser-1.0.1.dist-info/METADATA
shark_ser-1.0.1.dist-info/WHEEL
shark_ser-1.0.1.dist-info/top_level.txt
shark_ser-1.0.1.dist-info/RECORD
